AIchess/AIchess.py
AIchess/__init__.py
AI_Chess-2.0.8.dist-info/LICENSE
AI_Chess-2.0.8.dist-info/METADATA
AI_Chess-2.0.8.dist-info/WHEEL
AI_Chess-2.0.8.dist-info/top_level.txt
AI_Chess-2.0.8.dist-info/RECORD
